hie_rag/__init__.py
hie_rag/ai_client.py
hie_rag/hie_rag.py
hie_rag/process.py
hie_rag/split.py
hie_rag/tree_index.py
hie_rag/utils.py
hie_rag/vectordb.py
hie_rag-0.2.5.dist-info/licenses/LICENSE
hie_rag-0.2.5.dist-info/METADATA
hie_rag-0.2.5.dist-info/WHEEL
hie_rag-0.2.5.dist-info/top_level.txt
hie_rag-0.2.5.dist-info/RECORD
