Metadata-Version: 2.4
Name: hie_rag
Version: 0.2.5
Summary: A hierarchical RAG framework for chunks retrieval.
License: Apache License
License-File: LICENSE
Requires-Dist: python-dotenv==1.0.1
Requires-Dist: werkzeug==3.1.3
Requires-Dist: numpy
Requires-Dist: markitdown==0.0.1a3
Requires-Dist: openai==1.66.3
Requires-Dist: scikit-learn
Requires-Dist: tiktoken==0.8.0
Requires-Dist: langchain==0.3.13
Requires-Dist: langchain-ollama==0.3.3
Requires-Dist: chromadb==0.6.2
Dynamic: license-file
